Workbook

Sheet Ficha Resumen del Proyecto
B2: CONDOMINIO ECOLOGICO RÚSTICO DE LUJO - MOON PARACAS
B3: Ficha Resumen de Áreas, Tipologías y Parámetros Técnicos de Ingeniería
B5: 1. CUADRO RESUMEN DE DISTRIBUCIÓN DE ÁREAS (11.2 Hectáreas)
B6: Componente del Masterplan | C6: Área (m²) | D6: Porcentaje (%) | E6: Descripción Técnica
B7: Área Útil Vendible (Lotes y Cocheras) | C7: =E21+E27 | D7: =C7/$C$12 | E7: Superficie neta asignada a parcelas privadas de vivienda.
B8: Área Aportes (Amenidades / Oasis) | C8: 21149.13 | D8: =C8/$C$12 | E8: Parques comunes, piscina tipo oasis, espejo de agua y senderos Zen.
B9: Vías y Faja de Servidumbre | C9: 17137.84 | D9: =C9/$C$12 | E9: Vías de circulación interna de 6.0m de ancho y fajas peatonales.
B10: Retiro Perimetral y Residual | C10: 10107.39 | D10: =C10/$C$12 | E10: Margen de seguridad perimetral de amortiguamiento frente al entorno exterior.
B11: Buffer de Expansión / Reserva Técnica | C11: 5084.83 | D11: =C11/$C$12 | E11: Margen técnico de tierras liberado tras la re-ingeniería de cabidas útiles.
B12: ÁREA TOTAL TERRENO (MATRIZ) | C12: =SUM(C7:C11) | D12: =SUM(D7:D11) | E12: Validado matemáticamente al 100.00%
B14: 2. INVENTARIO RESUMEN DE LOTES COMERCIALES
B15: Tipología de Lote | C15: Lotes Vendibles | D15: Área Promedio (m²) | E15: Área Total (m²) | F15: Precio Base x m² | G15: Recaudación Proyectada
B16: Lote Premium (Oasis) | C16: =COUNTIF('Inventario Detallado'!D:D, "Lote Premium (Oasis)") | D16: =AVERAGEIF('Inventario Detallado'!D:D, "Lote Premium (Oasis)", 'Inventario Detallado'!E:E) | E16: =SUMIF('Inventario Detallado'!D:D, "Lote Premium (Oasis)", 'Inventario Detallado'!E:E) | F16: S/ 170/m² (Fase Estándar) | G16: =SUMIF('Inventario Detallado'!D:D, "Lote Premium (Oasis)", 'Inventario Detallado'!G:G)
B17: Lote Zen | C17: =COUNTIF('Inventario Detallado'!D:D, "Lote Zen") | D17: =AVERAGEIF('Inventario Detallado'!D:D, "Lote Zen", 'Inventario Detallado'!E:E) | E17: =SUMIF('Inventario Detallado'!D:D, "Lote Zen", 'Inventario Detallado'!E:E) | F17: S/ 120/m² (Fase Estándar) | G17: =SUMIF('Inventario Detallado'!D:D, "Lote Zen", 'Inventario Detallado'!G:G)
B18: Lote Estándar | C18: =COUNTIF('Inventario Detallado'!D:D, "Lote Estándar") | D18: =AVERAGEIF('Inventario Detallado'!D:D, "Lote Estándar", 'Inventario Detallado'!E:E) | E18: =SUMIF('Inventario Detallado'!D:D, "Lote Estándar", 'Inventario Detallado'!E:E) | F18: S/ 120/m² (Fase Estándar) | G18: =SUMIF('Inventario Detallado'!D:D, "Lote Estándar", 'Inventario Detallado'!G:G)
B19: Lote Tiny House | C19: =COUNTIF('Inventario Detallado'!D:D, "Lote Tiny House") | D19: =AVERAGEIF('Inventario Detallado'!D:D, "Lote Tiny House", 'Inventario Detallado'!E:E) | E19: =SUMIF('Inventario Detallado'!D:D, "Lote Tiny House", 'Inventario Detallado'!E:E) | F19: S/ 120/m² (Fase Estándar) | G19: =SUMIF('Inventario Detallado'!D:D, "Lote Tiny House", 'Inventario Detallado'!G:G)
B20: Lote Ajuste (Irregular) | C20: =COUNTIF('Inventario Detallado'!D:D, "Lote Ajuste (Irregular)") | D20: =AVERAGEIF('Inventario Detallado'!D:D, "Lote Ajuste (Irregular)", 'Inventario Detallado'!E:E) | E20: =SUMIF('Inventario Detallado'!D:D, "Lote Ajuste (Irregular)", 'Inventario Detallado'!E:E) | F20: S/ 120/m² (Fase Estándar) | G20: =SUMIF('Inventario Detallado'!D:D, "Lote Ajuste (Irregular)", 'Inventario Detallado'!G:G)
B21: Subtotal Lotes Residenciales | C21: =SUM(C16:C20) | D21: =AVERAGEIF('Inventario Detallado'!D:D, "Lote*", 'Inventario Detallado'!E:E) | E21: =SUM(E16:E20) | G21: =SUM(G16:G20)
B23: 3. COMPONENTE DE ESTACIONAMIENTOS INTERNOS Y EXTERNOS
B24: Tipo de Cochera | C24: Unidades | D24: Área Unit. (m²) | E24: Área Total (m²) | F24: Precio Venta (S/) | G24: Recaudación Proyectada
B25: Cochera Plus (Propiedad Privada) | C25: =COUNTIF('Inventario Detallado'!D:D, "Cochera Plus") | D25: 12.5 | E25: =SUMIF('Inventario Detallado'!D:D, "Cochera Plus", 'Inventario Detallado'!E:E) | F25: 5000 | G25: =SUMIF('Inventario Detallado'!D:D, "Cochera Plus", 'Inventario Detallado'!G:G)
B26: Cochera Visitas (Pública / Libre de Pago) | C26: =COUNTIF('Inventario Detallado'!D:D, "Cochera Visitas (Pública)") | D26: 12.5 | E26: =SUMIF('Inventario Detallado'!D:D, "Cochera Visitas (Pública)", 'Inventario Detallado'!E:E) | F26: 0 | G26: 0
B27: Subtotal Estacionamientos | C27: =SUM(C25:C26) | E27: =SUM(E25:E26) | G27: =SUM(G25:G26)
B29: RECAUDACIÓN Y VALORIZACIÓN CONSOLIDADA
B30: Recaudación Proyectada Lotes | G30: =G21
B31: Recaudación Proyectada Cocheras Privadas | G31: =G27
B32: PROYECCIÓN TOTAL BRUTA DEL PROYECTO (100% VENDIDO) | G32: =G30+G31

Sheet Lotes Disponibles
B2: CONDOMINIO ECOLOGICO RÚSTICO DE LUJO - MOON PARACAS
B3: Inventario Técnico de Lotes Disponibles y en Oferta Especial
B5: LOTES DISPONIBLES | D5: ÁREA DISPONIBLE (m²) | F5: VALOR COMERCIAL (S/) | H5: VALOR TOTAL DE OBRA (S/)
B6: =COUNTIF('Inventario Detallado'!J2:J451, "Disponible") + COUNTIF('Inventario Detallado'!J2:J451, "En Oferta") | D6: =SUMIF('Inventario Detallado'!J2:J451, "Disponible", 'Inventario Detallado'!E2:E451) + SUMIF('Inventario Detallado'!J2:J451, "En Oferta", 'Inventario Detallado'!E2:E451) | F6: =SUMIF('Inventario Detallado'!J2:J451, "Disponible", 'Inventario Detallado'!G2:G451) + SUMIF('Inventario Detallado'!J2:J451, "En Oferta", 'Inventario Detallado'!G2:G451) | H6: ='Presupuesto de Obras'!G37
A9: ID Lote | B9: Nombre Comercial | C9: Manzana | D9: Tipología | E9: Área útil (m²) | F9: Dimensiones | G9: Precio Venta (S/) | H9: Dist. Oasis (m) | I9: Dist. Cocheras (m) | J9: Estado Comercial
A10: L001 | B10: Lote 1 | C10: M1 | D10: Lote Estándar | E10: ='Inventario Detallado'!E2 | F10: 12.16m x 18.75m | G10: ='Inventario Detallado'!G2 | H10: 106 | I10: 14 | J10: Disponible
A11: L002 | B11: Lote 2 | C11: M1 | D11: Lote Estándar | E11: ='Inventario Detallado'!E3 | F11: 12.16m x 18.67m | G11: ='Inventario Detallado'!G3 | H11: 106 | I11: 26 | J11: Disponible
A12: L003 | B12: Lote 3 | C12: M1 | D12: Lote Estándar | E12: ='Inventario Detallado'!E4 | F12: 12.16m x 18.64m | G12: ='Inventario Detallado'!G4 | H12: 106 | I12: 39 | J12: Disponible
A13: L004 | B13: Lote 4 | C13: M1 | D13: Lote Estándar | E13: ='Inventario Detallado'!E5 | F13: 12.18m x 18.66m | G13: ='Inventario Detallado'!G5 | H13: 107 | I13: 51 | J13: Disponible
A14: L006 | B14: Lote 6 | C14: M1 | D14: Lote Estándar | E14: ='Inventario Detallado'!E7 | F14: 12.18m x 18.86m | G14: ='Inventario Detallado'!G7 | H14: 109 | I14: 75 | J14: Disponible
A15: L007 | B15: Lote 7 | C15: M1 | D15: Lote Estándar | E15: ='Inventario Detallado'!E8 | F15: 12.18m x 19.02m | G15: ='Inventario Detallado'!G8 | H15: 110 | I15: 88 | J15: Disponible
A16: L008 | B16: Lote 8 | C16: M2 | D16: Lote Estándar | E16: ='Inventario Detallado'!E9 | F16: 12.07m x 19.26m | G16: ='Inventario Detallado'!G9 | H16: 112 | I16: 105 | J16: Disponible
A17: L009 | B17: Lote 9 | C17: M2 | D17: Lote Estándar | E17: ='Inventario Detallado'!E10 | F17: 12.07m x 19.34m | G17: ='Inventario Detallado'!G10 | H17: 112 | I17: 117 | J17: Disponible
A18: L010 | B18: Lote 10 | C18: M2 | D18: Lote Estándar | E18: ='Inventario Detallado'!E11 | F18: 12.07m x 19.37m | G18: ='Inventario Detallado'!G11 | H18: 112 | I18: 129 | J18: Disponible
A19: L011 | B19: Lote 11 | C19: M2 | D19: Lote Estándar | E19: ='Inventario Detallado'!E12 | F19: 12.07m x 19.39m | G19: ='Inventario Detallado'!G12 | H19: 112 | I19: 141 | J19: Disponible
A20: L012 | B20: Lote 12 | C20: M2 | D20: Lote Estándar | E20: ='Inventario Detallado'!E13 | F20: 12.07m x 19.42m | G20: ='Inventario Detallado'!G13 | H20: 112 | I20: 145 | J20: Disponible
A21: L013 | B21: Lote 13 | C21: M2 | D21: Lote Estándar | E21: ='Inventario Detallado'!E14 | F21: 12.07m x 19.45m | G21: ='Inventario Detallado'!G14 | H21: 112 | I21: 145 | J21: Disponible
A22: L015 | B22: Lote 15 | C22: M2 | D22: Lote Estándar | E22: ='Inventario Detallado'!E16 | F22: 12.07m x 19.50m | G22: ='Inventario Detallado'!G16 | H22: 113 | I22: 145 | J22: Disponible
A23: L016 | B23: Lote 16 | C23: M2 | D23: Lote Estándar | E23: ='Inventario Detallado'!E17 | F23: 12.07m x 19.52m | G23: ='Inventario Detallado'!G17 | H23: 113 | I23: 145 | J23: Disponible
A24: L017 | B24: Lote 17 | C24: M2 | D24: Lote Estándar | E24: ='Inventario Detallado'!E18 | F24: 12.07m x 19.55m | G24: ='Inventario Detallado'!G18 | H24: 112 | I24: 133 | J24: Disponible
A25: L018 | B25: Lote 18 | C25: M3 | D25: Lote Estándar | E25: ='Inventario Detallado'!E19 | F25: 12.54m x 19.53m | G25: ='Inventario Detallado'!G19 | H25: 111 | I25: 115 | J25: Disponible
A26: L019 | B26: Lote 19 | C26: M3 | D26: Lote Estándar | E26: ='Inventario Detallado'!E20 | F26: 12.54m x 19.42m | G26: ='Inventario Detallado'!G20 | H26: 110 | I26: 103 | J26: Disponible
A27: L020 | B27: Lote 20 | C27: M3 | D27: Lote Estándar | E27: ='Inventario Detallado'!E21 | F27: 12.54m x 19.29m | G27: ='Inventario Detallado'!G21 | H27: 109 | I27: 91 | J27: Disponible
A28: L021 | B28: Lote 21 | C28: M3 | D28: Lote Estándar | E28: ='Inventario Detallado'!E22 | F28: 12.54m x 19.19m | G28: ='Inventario Detallado'!G22 | H28: 109 | I28: 78 | J28: Disponible
A29: L022 | B29: Lote 22 | C29: M3 | D29: Lote Estándar | E29: ='Inventario Detallado'!E23 | F29: 12.56m x 19.15m | G29: ='Inventario Detallado'!G23 | H29: 109 | I29: 65 | J29: Disponible
A30: L023 | B30: Lote 23 | C30: M3 | D30: Lote Estándar | E30: ='Inventario Detallado'!E24 | F30: 12.56m x 19.16m | G30: ='Inventario Detallado'!G24 | H30: 110 | I30: 53 | J30: Disponible
A31: L024 | B31: Lote 24 | C31: M3 | D31: Lote Estándar | E31: ='Inventario Detallado'!E25 | F31: 12.56m x 19.22m | G31: ='Inventario Detallado'!G25 | H31: 110 | I31: 40 | J31: Disponible
A32: L025 | B32: Lote 25 | C32: M3 | D32: Lote Estándar | E32: ='Inventario Detallado'!E26 | F32: 12.56m x 19.34m | G32: ='Inventario Detallado'!G26 | H32: 111 | I32: 28 | J32: Disponible
A33: L026 | B33: Lote 26 | C33: M3 | D33: Lote Estándar | E33: ='Inventario Detallado'!E27 | F33: 12.56m x 19.51m | G33: ='Inventario Detallado'!G27 | H33: 113 | I33: 15 | J33: Disponible
... A39: L032 | B39: Lote 32 | C39: M4 | D39: Lote Estándar | E39: ='Inventario Detallado'!E33 | F39: 12.19m x 13.01m | G39: ='Inventario Detallado'!G33 | H39: 85 | I39: 75 | J39: Disponible
A40: L034 | B40: Lote 34 | C40: M5 | D40: Lote Estándar | E40: ='Inventario Detallado'!E35 | F40: 12.07m x 13.28m | G40: ='Inventario Detallado'!G35 | H40: 87 | I40: 105 | J40: Disponible
A41: L035 | B41: Lote 35 | C41: M5 | D41: Lote Estándar | E41: ='Inventario Detallado'!E36 | F41: 12.07m x 13.34m | G41: ='Inventario Detallado'!G36 | H41: 87 | I41: 116 | J41: Disponible
A42: L036 | B42: Lote 36 | C42: M5 | D42: Lote Estándar | E42: ='Inventario Detallado'!E37 | F42: 12.07m x 13.36m | G42: ='Inventario Detallado'!G37 | H42: 87 | I42: 128 | J42: Disponible
A43: L037 | B43: Lote 37 | C43: M5 | D43: Lote Estándar | E43: ='Inventario Detallado'!E38 | F43: 12.07m x 13.38m | G43: ='Inventario Detallado'!G38 | H43: 88 | I43: 140 | J43: Disponible
A44: L038 | B44: Lote 38 | C44: M5 | D44: Lote Estándar | E44: ='Inventario Detallado'!E39 | F44: 12.07m x 13.39m | G44: ='Inventario Detallado'!G39 | H44: 88 | I44: 145 | J44: Disponible
A45: L039 | B45: Lote 39 | C45: M5 | D45: Lote Estándar | E45: ='Inventario Detallado'!E40 | F45: 12.07m x 13.41m | G45: ='Inventario Detallado'!G40 | H45: 88 | I45: 145 | J45: Disponible
A46: L040 | B46: Lote 40 | C46: M5 | D46: Lote Estándar | E46: ='Inventario Detallado'!E41 | F46: 12.07m x 13.43m | G46: ='Inventario Detallado'!G41 | H46: 88 | I46: 145 | J46: Disponible
A47: L041 | B47: Lote 41 | C47: M5 | D47: Lote Estándar | E47: ='Inventario Detallado'!E42 | F47: 12.07m x 13.45m | G47: ='Inventario Detallado'!G42 | H47: 88 | I47: 145 | J47: Disponible
A48: L042 | B48: Lote 42 | C48: M5 | D48: Lote Estándar | E48: ='Inventario Detallado'!E43 | F48: 12.07m x 13.46m | G48: ='Inventario Detallado'!G43 | H48: 88 | I48: 145 | J48: Disponible
A49: L043 | B49: Lote 43 | C49: M5 | D49: Lote Estándar | E49: ='Inventario Detallado'!E44 | F49: 12.07m x 13.48m | G49: ='Inventario Detallado'!G44 | H49: 88 | I49: 133 | J49: Disponible
A50: L044 | B50: Lote 44 | C50: M6 | D50: Lote Estándar | E50: ='Inventario Detallado'!E45 | F50: 12.55m x 13.47m | G50: ='Inventario Detallado'!G45 | H50: 86 | I50: 116 | J50: Disponible
A51: L045 | B51: Lote 45 | C51: M6 | D51: Lote Estándar | E51: ='Inventario Detallado'!E46 | F51: 12.55m x 13.39m | G51: ='Inventario Detallado'!G46 | H51: 86 | I51: 103 | J51: Disponible
A52: L046 | B52: Lote 46 | C52: M6 | D52: Lote Estándar | E52: ='Inventario Detallado'!E47 | F52: 12.55m x 13.30m | G52: ='Inventario Detallado'!G47 | H52: 85 | I52: 91 | J52: Disponible
A53: L048 | B53: Lote 48 | C53: M6 | D53: Lote Estándar | E53: ='Inventario Detallado'!E49 | F53: 12.57m x 13.20m | G53: ='Inventario Detallado'!G49 | H53: 85 | I53: 65 | J53: Disponible
A54: L049 | B54: Lote 49 | C54: M6 | D54: Lote Estándar | E54: ='Inventario Detallado'!E50 | F54: 12.57m x 13.21m | G54: ='Inventario Detallado'!G50 | H54: 85 | I54: 53 | J54: Disponible
A55: L050 | B55: Lote 50 | C55: M6 | D55: Lote Estándar | E55: ='Inventario Detallado'!E51 | F55: 12.57m x 13.26m | G55: ='Inventario Detallado'!G51 | H55: 86 | I55: 40 | J55: Disponible
A56: L051 | B56: Lote 51 | C56: M6 | D56: Lote Estándar | E56: ='Inventario Detallado'!E52 | F56: 12.57m x 13.34m | G56: ='Inventario Detallado'!G52 | H56: 87 | I56: 28 | J56: Disponible
A57: L052 | B57: Lote 52 | C57: M6 | D57: Lote Estándar | E57: ='Inventario Detallado'!E53 | F57: 12.57m x 13.45m | G57: ='Inventario Detallado'!G53 | H57: 88 | I57: 15 | J57: Disponible
A58: L053 | B58: Lote 53 | C58: M7 | D58: Lote Tiny House | E58: ='Inventario Detallado'!E54 | F58: 12.16m x 9.38m | G58: ='Inventario Detallado'!G54 | H58: 64 | I58: 25 | J58: Disponible
A59: L054 | B59: Lote 54 | C59: M7 | D59: Lote Tiny House | E59: ='Inventario Detallado'!E55 | F59: 12.16m x 9.34m | G59: ='Inventario Detallado'!G55 | H59: 64 | I59: 32 | J59: Disponible
A60: L056 | B60: Lote 56 | C60: M7 | D60: Lote Tiny House | E60: ='Inventario Detallado'!E57 | F60: 12.19m x 9.33m | G60: ='Inventario Detallado'!G57 | H60: 64 | I60: 53 | J60: Disponible
A61: L057 | B61: Lote 57 | C61: M7 | D61: Lote Tiny House | E61: ='Inventario Detallado'!E58 | F61: 12.19m x 9.37m | G61: ='Inventario Detallado'!G58 | H61: 65 | I61: 64 | J61: Disponible
A62: L058 | B62: Lote 58 | C62: M7 | D62: Lote Tiny House | E62: ='Inventario Detallado'!E59 | F62: 12.19m x 9.43m | G62: ='Inventario Detallado'!G59 | H62: 65 | I62: 76 | J62: Disponible
A63: L059 | B63: Lote 59 | C63: M7 | D63: Lote Tiny House | E63: ='Inventario Detallado'!E60 | F63: 12.19m x 9.51m | G63: ='Inventario Detallado'!G60 | H63: 66 | I63: 88 | J63: Disponible
A64: L060 | B64: Lote 60 | C64: M7 | D64: Lote Tiny House | E64: ='Inventario Detallado'!E61 | F64: 12.17m x 9.38m | G64: ='Inventario Detallado'!G61 | H64: 55 | I64: 25 | J64: En Oferta
A65: L062 | B65: Lote 62 | C65: M7 | D65: Lote Tiny House | E65: ='Inventario Detallado'!E63 | F65: 12.17m x 9.32m | G65: ='Inventario Detallado'!G63 | H65: 54 | I65: 46 | J65: En Oferta
A66: L063 | B66: Lote 63 | C66: M7 | D66: Lote Tiny House | E66: ='Inventario Detallado'!E64 | F66: 12.19m x 9.33m | G66: ='Inventario Detallado'!G64 | H66: 55 | I66: 56 | J66: Disponible
A67: L064 | B67: Lote 64 | C67: M7 | D67: Lote Tiny House | E67: ='Inventario Detallado'!E65 | F67: 12.19m x 9.37m | G67: ='Inventario Detallado'!G65 | H67: 55 | I67: 67 | J67: En Oferta
A68: L065 | B68: Lote 65 | C68: M7 | D68: Lote Tiny House | E68: ='Inventario Detallado'!E66 | F68: 12.19m x 9.43m | G68: ='Inventario Detallado'!G66 | H68: 56 | I68: 78 | J68: En Oferta
A69: L066 | B69: Lote 66 | C69: M7 | D69: Lote Tiny House | E69: ='Inventario Detallado'!E67 | F69: 12.19m x 9.51m | G69: ='Inventario Detallado'!G67 | H69: 57 | I69: 90 | J69: Disponible
A70: L067 | B70: Lote 67 | C70: M8 | D70: Lote Tiny House | E70: ='Inventario Detallado'!E68 | F70: 12.07m x 9.63m | G70: ='Inventario Detallado'!G68 | H70: 68 | I70: 105 | J70: Disponible
A71: L068 | B71: Lote 68 | C71: M8 | D71: Lote Tiny House | E71: ='Inventario Detallado'!E69 | F71: 12.08m x 9.67m | G71: ='Inventario Detallado'!G69 | H71: 68 | I71: 117 | J71: Disponible
A72: L069 | B72: Lote 69 | C72: M8 | D72: Lote Tiny House | E72: ='Inventario Detallado'!E70 | F72: 12.08m x 9.68m | G72: ='Inventario Detallado'!G70 | H72: 68 | I72: 129 | J72: Disponible
A73: L070 | B73: Lote 70 | C73: M8 | D73: Lote Tiny House | E73: ='Inventario Detallado'!E71 | F73: 12.08m x 9.70m | G73: ='Inventario Detallado'!G71 | H73: 68 | I73: 141 | J73: Disponible
A74: L071 | B74: Lote 71 | C74: M8 | D74: Lote Tiny House | E74: ='Inventario Detallado'!E72 | F74: 12.08m x 9.71m | G74: ='Inventario Detallado'!G72 | H74: 68 | I74: 145 | J74: Disponible
A75: L072 | B75: Lote 72 | C75: M8 | D75: Lote Tiny House | E75: ='Inventario Detallado'!E73 | F75: 12.08m x 9.72m | G75: ='Inventario Detallado'!G73 | H75: 68 | I75: 145 | J75: En Oferta
A76: L073 | B76: Lote 73 | C76: M8 | D76: Lote Tiny House | E76: ='Inventario Detallado'!E74 | F76: 12.08m x 9.74m | G76: ='Inventario Detallado'!G74 | H76: 68 | I76: 145 | J76: Disponible
... A83: L080 | B83: Lote 80 | C83: M8 | D83: Lote Tiny House | E83: ='Inventario Detallado'!E81 | F83: 12.08m x 9.70m | G83: ='Inventario Detallado'!G81 | H83: 58 | I83: 141 | J83: En Oferta
A84: L082 | B84: Lote 82 | C84: M8 | D84: Lote Tiny House | E84: ='Inventario Detallado'!E83 | F84: 12.08m x 9.72m | G84: ='Inventario Detallado'!G83 | H84: 58 | I84: 145 | J84: En Oferta
A85: L083 | B85: Lote 83 | C85: M8 | D85: Lote Tiny House | E85: ='Inventario Detallado'!E84 | F85: 12.08m x 9.74m | G85: ='Inventario Detallado'!G84 | H85: 58 | I85: 145 | J85: Disponible
A86: L084 | B86: Lote 84 | C86: M8 | D86: Lote Tiny House | E86: ='Inventario Detallado'!E85 | F86: 12.08m x 9.75m | G86: ='Inventario Detallado'!G85 | H86: 59 | I86: 145 | J86: Disponible
A87: L085 | B87: Lote 85 | C87: M8 | D87: Lote Tiny House | E87: ='Inventario Detallado'!E86 | F87: 12.08m x 9.76m | G87: ='Inventario Detallado'!G86 | H87: 59 | I87: 145 | J87: Disponible
A88: L086 | B88: Lote 86 | C88: M8 | D88: Lote Tiny House | E88: ='Inventario Detallado'!E87 | F88: 12.08m x 9.77m | G88: ='Inventario Detallado'!G87 | H88: 59 | I88: 133 | J88: Disponible
A89: L087 | B89: Lote 87 | C89: M9 | D89: Lote Tiny House | E89: ='Inventario Detallado'!E88 | F89: 12.56m x 9.76m | G89: ='Inventario Detallado'!G88 | H89: 67 | I89: 116 | J89: Disponible
A90: L088 | B90: Lote 88 | C90: M9 | D90: Lote Tiny House | E90: ='Inventario Detallado'!E89 | F90: 12.56m x 9.71m | G90: ='Inventario Detallado'!G89 | H90: 66 | I90: 103 | J90: Disponible
A91: L089 | B91: Lote 89 | C91: M9 | D91: Lote Tiny House | E91: ='Inventario Detallado'!E90 | F91: 12.56m x 9.64m | G91: ='Inventario Detallado'!G90 | H91: 66 | I91: 91 | J91: Disponible
A92: L090 | B92: Lote 90 | C92: M9 | D92: Lote Tiny House | E92: ='Inventario Detallado'!E91 | F92: 12.56m x 9.60m | G92: ='Inventario Detallado'!G91 | H92: 65 | I92: 78 | J92: Disponible
A93: L091 | B93: Lote 91 | C93: M9 | D93: Lote Tiny House | E93: ='Inventario Detallado'!E92 | F93: 12.58m x 9.57m | G93: ='Inventario Detallado'!G92 | H93: 65 | I93: 65 | J93: Disponible
A94: L092 | B94: Lote 92 | C94: M9 | D94: Lote Tiny House | E94: ='Inventario Detallado'!E93 | F94: 12.58m x 9.58m | G94: ='Inventario Detallado'!G93 | H94: 66 | I94: 53 | J94: Disponible
A95: L093 | B95: Lote 93 | C95: M9 | D95: Lote Tiny House | E95: ='Inventario Detallado'!E94 | F95: 12.58m x 9.61m | G95: ='Inventario Detallado'!G94 | H95: 66 | I95: 40 | J95: Disponible
... A100: L098 | B100: Lote 98 | C100: M9 | D100: Lote Tiny House | E100: ='Inventario Detallado'!E99 | F100: 12.57m x 9.64m | G100: ='Inventario Detallado'!G99 | H100: 56 | I100: 91 | J100: Disponible
A101: L100 | B101: Lote 100 | C101: M9 | D101: Lote Tiny House | E101: ='Inventario Detallado'!E101 | F101: 12.58m x 9.57m | G101: ='Inventario Detallado'!G101 | H101: 56 | I101: 65 | J101: Disponible
A102: L101 | B102: Lote 101 | C102: M9 | D102: Lote Tiny House | E102: ='Inventario Detallado'!E102 | F102: 12.58m x 9.58m | G102: ='Inventario Detallado'!G102 | H102: 56 | I102: 53 | J102: Disponible
A103: L102 | B103: Lote 102 | C103: M9 | D103: Lote Tiny House | E103: ='Inventario Detallado'!E103 | F103: 12.58m x 9.61m | G103: ='Inventario Detallado'!G103 | H103: 57 | I103: 40 | J103: Disponible
A104: L103 | B104: Lote 103 | C104: M9 | D104: Lote Tiny House | E104: ='Inventario Detallado'!E104 | F104: 12.58m x 9.67m | G104: ='Inventario Detallado'!G104 | H104: 57 | I104: 28 | J104: Disponible
A105: L104 | B105: Lote 104 | C105: M9 | D105: Lote Tiny House | E105: ='Inventario Detallado'!E105 | F105: 12.58m x 9.75m | G105: ='Inventario Detallado'!G105 | H105: 58 | I105: 15 | J105: Disponible
A106: L105 | B106: Lote 105 | C106: M10 | D106: Lote Tiny House | E106: ='Inventario Detallado'!E106 | F106: 12.17m x 18.75m | G106: ='Inventario Detallado'!G106 | H106: 33 | I106: 33 | J106: Disponible
A107: L106 | B107: Lote 106 | C107: M10 | D107: Lote Tiny House | E107: ='Inventario Detallado'!E107 | F107: 12.17m x 18.67m | G107: ='Inventario Detallado'!G107 | H107: 33 | I107: 42 | J107: Disponible
A108: L107 | B108: Lote 107 | C108: M10 | D108: Lote Tiny House | E108: ='Inventario Detallado'!E108 | F108: 12.17m x 18.64m | G108: ='Inventario Detallado'!G108 | H108: 33 | I108: 52 | J108: Disponible
A109: L108 | B109: Lote 108 | C109: M10 | D109: Lote Tiny House | E109: ='Inventario Detallado'!E109 | F109: 12.19m x 18.66m | G109: ='Inventario Detallado'!G109 | H109: 33 | I109: 64 | J109: Disponible
A110: L109 | B110: Lote 109 | C110: M10 | D110: Lote Tiny House | E110: ='Inventario Detallado'!E110 | F110: 12.19m x 18.74m | G110: ='Inventario Detallado'!G110 | H110: 33 | I110: 75 | J110: Disponible
A111: L110 | B111: Lote 110 | C111: M10 | D111: Lote Tiny House | E111: ='Inventario Detallado'!E111 | F111: 12.19m x 18.86m | G111: ='Inventario Detallado'!G111 | H111: 34 | I111: 87 | J111: Disponible
A112: L111 | B112: Lote 111 | C112: M10 | D112: Lote Tiny House | E112: ='Inventario Detallado'!E112 | F112: 12.19m x 19.02m | G112: ='Inventario Detallado'!G112 | H112: 34 | I112: 97 | J112: Disponible
... A126: L125 | B126: Lote 125 | C126: M12 | D126: Lote Tiny House | E126: ='Inventario Detallado'!E126 | F126: 12.58m x 19.19m | G126: ='Inventario Detallado'!G126 | H126: 34 | I126: 79 | J126: Disponible
A127: L127 | B127: Lote 127 | C127: M12 | D127: Lote Tiny House | E127: ='Inventario Detallado'!E128 | F127: 12.59m x 19.15m | G127: ='Inventario Detallado'!G128 | H127: 34 | I127: 53 | J127: Disponible
A128: L128 | B128: Lote 128 | C128: M12 | D128: Lote Tiny House | E128: ='Inventario Detallado'!E129 | F128: 12.59m x 19.22m | G128: ='Inventario Detallado'!G129 | H128: 34 | I128: 41 | J128: Disponible
A129: L129 | B129: Lote 129 | C129: M12 | D129: Lote Tiny House | E129: ='Inventario Detallado'!E130 | F129: 12.59m x 19.34m | G129: ='Inventario Detallado'!G130 | H129: 35 | I129: 28 | J129: Disponible
A130: L130 | B130: Lote 130 | C130: M12 | D130: Lote Tiny House | E130: ='Inventario Detallado'!E131 | F130: 12.59m x 19.50m | G130: ='Inventario Detallado'!G131 | H130: 35 | I130: 15 | J130: Disponible
A131: L131 | B131: Lote 131 | C131: M13 | D131: Lote Premium (Oasis) | E131: ='Inventario Detallado'!E132 | F131: 12.20m x 18.93m | G131: ='Inventario Detallado'!G132 | H131: 3 | I131: 57 | J131: Disponible
A132: L132 | B132: Lote 132 | C132: M13 | D132: Lote Premium (Oasis) | E132: ='Inventario Detallado'!E133 | F132: 12.20m x 18.91m | G132: ='Inventario Detallado'!G133 | H132: 1 | I132: 63 | J132: Disponible
...

Sheet Inventario Detallado
A1: ID Elemento | B1: Nombre Comercial | C1: Manzana / Bloque | D1: Tipología | E1: Área Útil (m²) | F1: Dimensiones | G1: Precio Venta (S/) | H1: Dist. Oasis (m) | I1: Dist. Cocheras (m) | J1: Estado Comercial
A2: L001 | B2: Lote 1 | C2: M1 | D2: Lote Estándar | E2: 225.54 | F2: 12.16m x 18.75m | G2: =E2*120 | H2: 106 | I2: 14 | J2: Disponible
A3: L002 | B3: Lote 2 | C3: M1 | D3: Lote Estándar | E3: 224.67 | F3: 12.16m x 18.67m | G3: =E3*120 | H3: 106 | I3: 26 | J3: Disponible
A4: L003 | B4: Lote 3 | C4: M1 | D4: Lote Estándar | E4: 224.37 | F4: 12.16m x 18.64m | G4: =E4*120 | H4: 106 | I4: 39 | J4: Disponible
A5: L004 | B5: Lote 4 | C5: M1 | D5: Lote Estándar | E5: 225.14 | F5: 12.18m x 18.66m | G5: =E5*120 | H5: 107 | I5: 51 | J5: Disponible
A6: L005 | B6: Lote 5 | C6: M1 | D6: Lote Estándar | E6: 226.12 | F6: 12.18m x 18.74m | G6: =E6*120 | H6: 108 | I6: 63 | J6: Vendido
A7: L006 | B7: Lote 6 | C7: M1 | D7: Lote Estándar | E7: 227.66 | F7: 12.18m x 18.86m | G7: =E7*120 | H7: 109 | I7: 75 | J7: Disponible
A8: L007 | B8: Lote 7 | C8: M1 | D8: Lote Estándar | E8: 229.65 | F8: 12.18m x 19.02m | G8: =E8*120 | H8: 110 | I8: 88 | J8: Disponible
A9: L008 | B9: Lote 8 | C9: M2 | D9: Lote Estándar | E9: 230.62 | F9: 12.07m x 19.26m | G9: =E9*120 | H9: 112 | I9: 105 | J9: Disponible
A10: L009 | B10: Lote 9 | C10: M2 | D10: Lote Estándar | E10: 231.26 | F10: 12.07m x 19.34m | G10: =E10*120 | H10: 112 | I10: 117 | J10: Disponible
A11: L010 | B11: Lote 10 | C11: M2 | D11: Lote Estándar | E11: 231.58 | F11: 12.07m x 19.37m | G11: =E11*120 | H11: 112 | I11: 129 | J11: Disponible
A12: L011 | B12: Lote 11 | C12: M2 | D12: Lote Estándar | E12: 231.89 | F12: 12.07m x 19.39m | G12: =E12*120 | H12: 112 | I12: 141 | J12: Disponible
A13: L012 | B13: Lote 12 | C13: M2 | D13: Lote Estándar | E13: 232.2 | F13: 12.07m x 19.42m | G13: =E13*120 | H13: 112 | I13: 145 | J13: Disponible
... A60: L059 | B60: Lote 59 | C60: M7 | D60: Lote Tiny House | E60: 115.32 | F60: 12.19m x 9.51m | G60: =E60*120 | H60: 66 | I60: 88 | J60: Disponible
A61: L060 | B61: Lote 60 | C61: M7 | D61: Lote Tiny House | E61: 112.43 | F61: 12.17m x 9.38m | G61: =E61*60 | H61: 55 | I61: 25 | J61: En Oferta
A62: L061 | B62: Lote 61 | C62: M7 | D62: Lote Tiny House | E62: 112.18 | F62: 12.17m x 9.34m | G62: =E62*120 | H62: 54 | I62: 37 | J62: Separado
A63: L062 | B63: Lote 62 | C63: M7 | D63: Lote Tiny House | E63: 112.22 | F63: 12.17m x 9.32m | G63: =E63*60 | H63: 54 | I63: 46 | J63: En Oferta
A64: L063 | B64: Lote 63 | C64: M7 | D64: Lote Tiny House | E64: 112.79 | F64: 12.19m x 9.33m | G64: =E64*120 | H64: 55 | I64: 56 | J64: Disponible
A65: L064 | B65: Lote 64 | C65: M7 | D65: Lote Tiny House | E65: 113.43 | F65: 12.19m x 9.37m | G65: =E65*60 | H65: 55 | I65: 67 | J65: En Oferta
A66: L065 | B66: Lote 65 | C66: M7 | D66: Lote Tiny House | E66: 114.33 | F66: 12.19m x 9.43m | G66: =E66*60 | H66: 56 | I66: 78 | J66: En Oferta
A67: L066 | B67: Lote 66 | C67: M7 | D67: Lote Tiny House | E67: 115.41 | F67: 12.19m x 9.51m | G67: =E67*120 | H67: 57 | I67: 90 | J67: Disponible
A68: L067 | B68: Lote 67 | C68: M8 | D68: Lote Tiny House | E68: 115.71 | F68: 12.07m x 9.63m | G68: =E68*120 | H68: 68 | I68: 105 | J68: Disponible
A69: L068 | B69: Lote 68 | C69: M8 | D69: Lote Tiny House | E69: 115.75 | F69: 12.08m x 9.67m | G69: =E69*120 | H69: 68 | I69: 117 | J69: Disponible
A70: L069 | B70: Lote 69 | C70: M8 | D70: Lote Tiny House | E70: 115.91 | F70: 12.08m x 9.68m | G70: =E70*120 | H70: 68 | I70: 129 | J70: Disponible
A71: L070 | B71: Lote 70 | C71: M8 | D71: Lote Tiny House | E71: 116.06 | F71: 12.08m x 9.70m | G71: =E71*120 | H71: 68 | I71: 141 | J71: Disponible
A72: L071 | B72: Lote 71 | C72: M8 | D72: Lote Tiny House | E72: 116.22 | F72: 12.08m x 9.71m | G72: =E72*120 | H72: 68 | I72: 145 | J72: Disponible
A73: L072 | B73: Lote 72 | C73: M8 | D73: Lote Tiny House | E73: 116.38 | F73: 12.08m x 9.72m | G73: =E73*60 | H73: 68 | I73: 145 | J73: En Oferta
A74: L073 | B74: Lote 73 | C74: M8 | D74: Lote Tiny House | E74: 116.54 | F74: 12.08m x 9.74m | G74: =E74*120 | H74: 68 | I74: 145 | J74: Disponible
A75: L074 | B75: Lote 74 | C75: M8 | D75: Lote Tiny House | E75: 116.69 | F75: 12.08m x 9.75m | G75: =E75*120 | H75: 68 | I75: 145 | J75: Disponible
A76: L075 | B76: Lote 75 | C76: M8 | D76: Lote Tiny House | E76: 116.85 | F76: 12.08m x 9.76m | G76: =E76*120 | H76: 68 | I76: 145 | J76: Disponible
A77: L076 | B77: Lote 76 | C77: M8 | D77: Lote Tiny House | E77: 117.01 | F77: 12.08m x 9.77m | G77: =E77*120 | H77: 68 | I77: 133 | J77: Disponible
A78: L077 | B78: Lote 77 | C78: M8 | D78: Lote Tiny House | E78: 115.79 | F78: 12.07m x 9.63m | G78: =E78*60 | H78: 58 | I78: 106 | J78: En Oferta
A79: L078 | B79: Lote 78 | C79: M8 | D79: Lote Tiny House | E79: 115.78 | F79: 12.08m x 9.67m | G79: =E79*120 | H79: 58 | I79: 118 | J79: Disponible
A80: L079 | B80: Lote 79 | C80: M8 | D80: Lote Tiny House | E80: 115.94 | F80: 12.08m x 9.68m | G80: =E80*120 | H80: 58 | I80: 129 | J80: Disponible
A81: L080 | B81: Lote 80 | C81: M8 | D81: Lote Tiny House | E81: 116.09 | F81: 12.08m x 9.70m | G81: =E81*60 | H81: 58 | I81: 141 | J81: En Oferta
A82: L081 | B82: Lote 81 | C82: M8 | D82: Lote Tiny House | E82: 116.25 | F82: 12.08m x 9.71m | G82: =E82*120 | H82: 58 | I82: 145 | J82: Separado
A83: L082 | B83: Lote 82 | C83: M8 | D83: Lote Tiny House | E83: 116.41 | F83: 12.08m x 9.72m | G83: =E83*60 | H83: 58 | I83: 145 | J83: En Oferta
A84: L083 | B84: Lote 83 | C84: M8 | D84: Lote Tiny House | E84: 116.57 | F84: 12.08m x 9.74m | G84: =E84*120 | H84: 58 | I84: 145 | J84: Disponible
A85: L084 | B85: Lote 84 | C85: M8 | D85: Lote Tiny House | E85: 116.72 | F85: 12.08m x 9.75m | G85: =E85*120 | H85: 59 | I85: 145 | J85: Disponible
A86: L085 | B86: Lote 85 | C86: M8 | D86: Lote Tiny House | E86: 116.88 | F86: 12.08m x 9.76m | G86: =E86*120 | H86: 59 | I86: 145 | J86: Disponible
A87: L086 | B87: Lote 86 | C87: M8 | D87: Lote Tiny House | E87: 117.03 | F87: 12.08m x 9.77m | G87: =E87*120 | H87: 59 | I87: 133 | J87: Disponible
A88: L087 | B88: Lote 87 | C88: M9 | D88: Lote Tiny House | E88: 121.33 | F88: 12.56m x 9.76m | G88: =E88*120 | H88: 67 | I88: 116 | J88: Disponible
A89: L088 | B89: Lote 88 | C89: M9 | D89: Lote Tiny House | E89: 120.26 | F89: 12.56m x 9.71m | G89: =E89*120 | H89: 66 | I89: 103 | J89: Disponible
A90: L089 | B90: Lote 89 | C90: M9 | D90: Lote Tiny House | E90: 119.58 | F90: 12.56m x 9.64m | G90: =E90*120 | H90: 66 | I90: 91 | J90: Disponible
A91: L090 | B91: Lote 90 | C91: M9 | D91: Lote Tiny House | E91: 119.16 | F91: 12.56m x 9.60m | G91: =E91*120 | H91: 65 | I91: 78 | J91: Disponible
A92: L091 | B92: Lote 91 | C92: M9 | D92: Lote Tiny House | E92: 119.2 | F92: 12.58m x 9.57m | G92: =E92*120 | H92: 65 | I92: 65 | J92: Disponible
A93: L092 | B93: Lote 92 | C93: M9 | D93: Lote Tiny House | E93: 119.46 | F93: 12.58m x 9.58m | G93: =E93*120 | H93: 66 | I93: 53 | J93: Disponible
A94: L093 | B94: Lote 93 | C94: M9 | D94: Lote Tiny House | E94: 120.07 | F94: 12.58m x 9.61m | G94: =E94*120 | H94: 66 | I94: 40 | J94: Disponible
A95: L094 | B95: Lote 94 | C95: M9 | D95: Lote Tiny House | E95: 120.97 | F95: 12.58m x 9.67m | G95: =E95*120 | H95: 67 | I95: 28 | J95: Disponible
... A131: L130 | B131: Lote 130 | C131: M12 | D131: Lote Tiny House | E131: 245.02 | F131: 12.59m x 19.50m | G131: =E131*120 | H131: 35 | I131: 15 | J131: Disponible
A132: L131 | B132: Lote 131 | C132: M13 | D132: Lote Premium (Oasis) | E132: 230.11 | F132: 12.20m x 18.93m | G132: =E132*170 | H132: 3 | I132: 57 | J132: Disponible
A133: L132 | B133: Lote 132 | C133: M13 | D133: Lote Premium (Oasis) | E133: 229.44 | F133: 12.20m x 18.91m | G133: =E133*170 | H133: 1 | I133: 63 | J133: Disponible
A134: L133 | B134: Lote 133 | C134: M13 | D134: Lote Premium (Oasis) | E134: 228.94 | F134: 12.20m x 18.90m | G134: =E134*170 | H134: 1 | I134: 70 | J134: Disponible
A135: L134 | B135: Lote 134 | C135: M13 | D135: Lote Premium (Oasis) | E135: 229.1 | F135: 12.22m x 18.93m | G135: =E135*170 | H135: 1 | I135: 78 | J135: Disponible
A136: L135 | B136: Lote 135 | C136: M13 | D136: Lote Premium (Oasis) | E136: 229.1 | F136: 12.22m x 18.98m | G136: =E136*170 | H136: 1 | I136: 87 | J136: Disponible
A137: L136 | B137: Lote 136 | C137: M13 | D137: Lote Premium (Oasis) | E137: 229.42 | F137: 12.22m x 19.05m | G137: =E137*170 | H137: 3 | I137: 97 | J137: Disponible
A138: L137 | B138: Lote 137 | C138: M13 | D138: Lote Premium (Oasis) | E138: 230.1 | F138: 12.22m x 19.15m | G138: =E138*170 | H138: 5 | I138: 107 | J138: Separado
A139: L138 | B139: Lote 138 | C139: M14 | D139: Lote Premium (Oasis) | E139: 230.01 | F139: 12.09m x 19.29m | G139: =E139*170 | H139: 8 | I139: 122 | J139: Disponible
A140: L139 | B140: Lote 139 | C140: M14 | D140: Lote Premium (Oasis) | E140: 232.13 | F140: 12.10m x 19.34m | G140: =E140*170 | H140: 8 | I140: 133 | J140: Disponible
A141: L140 | B141: Lote 140 | C141: M14 | D141: Lote Premium (Oasis) | E141: 232.44 | F141: 12.10m x 19.37m | G141: =E141*170 | H141: 8 | I141: 144 | J141: Disponible
A142: L141 | B142: Lote 141 | C142: M14 | D142: Lote Premium (Oasis) | E142: 232.75 | F142: 12.10m x 19.39m | G142: =E142*170 | H142: 8 | I142: 145 | J142: Disponible
A143: L142 | B143: Lote 142 | C143: M14 | D143: Lote Premium (Oasis) | E143: 233.07 | F143: 12.10m x 19.42m | G143: =E143*170 | H143: 8 | I143: 145 | J143: Disponible
... A183: L182 | B183: Lote 182 | C183: M18 | D183: Lote Premium (Oasis) | E183: 244.28 | F183: 12.58m x 19.64m | G183: =E183*170 | H183: 12 | I183: 15 | J183: Disponible
A184: L183 | B184: Lote 183 | C184: M19 | D184: Lote Estándar | E184: 229.9 | F184: 12.20m x 18.93m | G184: =E184*120 | H184: 38 | I184: 26 | J184: Disponible
A185: L184 | B185: Lote 184 | C185: M19 | D185: Lote Estándar | E185: 229.38 | F185: 12.20m x 18.91m | G185: =E185*120 | H185: 38 | I185: 38 | J185: Disponible
A186: L185 | B186: Lote 185 | C186: M19 | D186: Lote Estándar | E186: 229.1 | F186: 12.20m x 18.90m | G186: =E186*120 | H186: 37 | I186: 50 | J186: Disponible
A187: L186 | B187: Lote 186 | C187: M19 | D187: Lote Estándar | E187: 229.56 | F187: 12.23m x 18.93m | G187: =E187*120 | H187: 37 | I187: 63 | J187: Disponible
A188: L187 | B188: Lote 187 | C188: M19 | D188: Lote Estándar | E188: 229.9 | F188: 12.23m x 18.98m | G188: =E188*120 | H188: 37 | I188: 75 | J188: Disponible
A189: L188 | B189: Lote 188 | C189: M19 | D189: Lote Estándar | E189: 230.56 | F189: 12.23m x 19.05m | G189: =E189*120 | H189: 38 | I189: 87 | J189: Disponible
A190: L189 | B190: Lote 189 | C190: M19 | D190: Lote Estándar | E190: 231.52 | F190: 12.22m x 19.15m | G190: =E190*120 | H190: 38 | I190: 99 | J190: Disponible
A191: L190 | B191: Lote 190 | C191: M20 | D191: Lote Zen | E191: 231.34 | F191: 12.11m x 19.29m | G191: =E191*120 | H191: 40 | I191: 117 | J191: Disponible
A192: L191 | B192: Lote 191 | C192: M20 | D192: Lote Zen | E192: 232.59 | F192: 12.11m x 19.34m | G192: =E192*120 | H192: 41 | I192: 129 | J192: Disponible
A193: L192 | B193: Lote 192 | C193: M20 | D193: Lote Zen | E193: 232.9 | F193: 12.11m x 19.37m | G193: =E193*120 | H193: 41 | I193: 141 | J193: Disponible
A194: L193 | B194: Lote 193 | C194: M20 | D194: Lote Zen | E194: 233.21 | F194: 12.11m x 19.39m | G194: =E194*120 | H194: 41 | I194: 145 | J194: Disponible
A195: L194 | B195: Lote 194 | C195: M20 | D195: Lote Zen | E195: 233.52 | F195: 12.11m x 19.42m | G195: =E195*120 | H195: 41 | I195: 145 | J195: Disponible
... A313: L312 | B313: Lote 312 | C313: M30 | D313: Lote Ajuste (Irregular) | E313: 246.2 | F313: 12.61m x 19.64m | G313: =E313*120 | H313: 116 | I313: 16 | J313: Disponible
A314: P001 | B314: P1 | C314: PARKING | D314: Cochera Plus | E314: 12.5 | F314: 2.5m x 5.0m | G314: =5000 | H314: 50 | I314: 0 | J314: Disponible
A315: P002 | B315: P2 | C315: PARKING | D315: Cochera Plus | E315: 12.5 | F315: 2.5m x 5.0m | G315: =5000 | H315: 50 | I315: 0 | J315: Disponible
A316: P003 | B316: P3 | C316: PARKING | D316: Cochera Plus | E316: 12.5 | F316: 2.5m x 5.0m | G316: =5000 | H316: 50 | I316: 0 | J316: Disponible
A317: P004 | B317: P4 | C317: PARKING | D317: Cochera Plus | E317: 12.5 | F317: 2.5m x 5.0m | G317: =5000 | H317: 50 | I317: 0 | J317: Disponible
A318: P005 | B318: P5 | C318: PARKING | D318: Cochera Plus | E318: 12.5 | F318: 2.5m x 5.0m | G318: =5000 | H318: 50 | I318: 0 | J318: Disponible
A319: P006 | B319: P6 | C319: PARKING | D319: Cochera Plus | E319: 12.5 | F319: 2.5m x 5.0m | G319: =5000 | H319: 50 | I319: 0 | J319: Disponible
A320: P007 | B320: P7 | C320: PARKING | D320: Cochera Plus | E320: 12.5 | F320: 2.5m x 5.0m | G320: =5000 | H320: 50 | I320: 0 | J320: Disponible
A321: P008 | B321: P8 | C321: PARKING | D321: Cochera Plus | E321: 12.5 | F321: 2.5m x 5.0m | G321: =5000 | H321: 50 | I321: 0 | J321: Disponible
A322: P009 | B322: P9 | C322: PARKING | D322: Cochera Plus | E322: 12.5 | F322: 2.5m x 5.0m | G322: =5000 | H322: 50 | I322: 0 | J322: Disponible
A323: P010 | B323: P10 | C323: PARKING | D323: Cochera Plus | E323: 12.5 | F323: 2.5m x 5.0m | G323: =5000 | H323: 50 | I323: 0 | J323: Disponible
A324: P011 | B324: P11 | C324: PARKING | D324: Cochera Plus | E324: 12.5 | F324: 2.5m x 5.0m | G324: =5000 | H324: 50 | I324: 0 | J324: Disponible
A325: P012 | B325: P12 | C325: PARKING | D325: Cochera Plus | E325: 12.5 | F325: 2.5m x 5.0m | G325: =5000 | H325: 50 | I325: 0 | J325: Disponible
... A451: P138 | B451: P138 | C451: PARKING | D451: Cochera Plus | E451: 12.5 | F451: 2.5m x 5.0m | G451: =5000 | H451: 50 | I451: 0 | J451: Disponible
A452: TOTAL GENERAL | E452: =SUM(E2:E451) | G452: =SUM(G2:G451)

Sheet Especificaciones Técnicas
B2: PARÁMETROS TÉCNICOS Y NORMAS CONSTRUCTIVAS
B3: Asociación Civil de Adjudicatarios Moon Paracas · Normativa Técnica
B5: 1. PARÁMETROS GEOTÉCNICOS Y CIMENTACIONES
B6: Parámetro Técnico | C6: Norma / Exigencia | D6: Sustentación de Ingeniería
B7: Clasificación Sísmica | C7: Zona Sísmica 4 (S1) | D7: Terreno de alta sismicidad según RNE E.030. Exige plateas de cimentación rígidas obligatorias para disipar esfuerzos sísmicos y evitar asentamientos diferenciales sobre arena.
B8: Resistencia de Cemento | C8: Cemento Portland Tipo V | D8: Presencia de sales y sulfatos en el suelo árido costero. El Cemento Tipo V garantiza inmunidad frente al ataque químico del salitre, asegurando una vida útil > 50 años.
B9: Resistencia del Concreto | C9: f'c >= 210 kg/cm² | D9: Mínimo especificado para todos los elementos estructurales y plateas de cimentación.
B10: Cota Topográfica Mínima | C10: 106.50 m s.n.m. (Ingreso) | D10: El emplazamiento en la meseta del tablazo elimina al 100% el riesgo sísmico por tsunami o subidas de marea.
B11: Cota Topográfica Máxima | C11: 113.50 m s.n.m. (Mirador) | D11: Gradiente topográfica suave de sur a norte (0.5% a 1%) que optimiza la evacuación de aguas de escorrentía pluvial.
B12: Diseño de Vías Internas | C12: Ancho de 6.00 metros | D12: Vías de tierra compactada estabilizada con emulsiones orgánicas para cero polvo. Restringidas exclusivamente a peatones, bicicletas y buggies eléctricos.
B15: 2. REGLAMENTO INTERNO DE CONSTRUCCIÓN Y ESTILO (ANEXO B)
B16: Elemento de Fachada | C16: Exigencia Estética | D16: Materiales Autorizados / Restricciones
B17: Muros y Fachadas | C17: Tonos terrosos y arena (Mimetismo desértico) | D17: Acabados en revoque rústico de barro texturizado, microcemento arena, u ocre. Se prohíben colores primarios brillantes o revestimientos metálicos industriales.
B18: Pircas de División | C18: Piedra de cantera local apilada a mano | D18: Muros bajos (máximo 1.20m de altura) para deslindar linderos, usando piedra caliza caliche dorada de Paracas. Prohibido cercos de alambre de púas o ladrillo expuesto sin tarrajeo.
B19: Pérgolas y Sombras | C19: Pórticos rústicos de madera noble | D19: Uso obligatorio de troncos o listones macizos de eucalipto seco tratado, caña brava o bambú chancado para terrazas y cocheras.
B20: Energía Autónoma | C20: Sistemas solares fotovoltaicos independientes | D20: Obligatoriedad de destinar un área en el techo plano para un mínimo de 4 paneles solares monocristalinos y baterías de litio. No se permite tendido eléctrico aéreo visible.
B21: Xeripaisajismo | C21: Uso de flora nativa de bajo consumo hídrico | D21: Vegetación obligatoria en linderos delanteros: Agaves americanos, cactus candelabro, huarangos y buganvilias. Prohibido el sembrado de césped americano que exija riego por inundación.

Sheet Presupuesto de Obras
B2: PRESUPUESTO DE INVERSIÓN EN OBRAS (CAPEX)
B3: Moon Paracas · Estimación técnica de infraestructura rústica de lujo
B5: 1. DETALLE DE PARTIDAS Y COSTOS DIRECTOS
B6: Item | C6: Descripción de Partida | D6: Unidad | E6: Metrado / Cantidad | F6: Precio Unitario (S/) | G6: Costo Total (S/) | H6: Materiales y Acabados Predominantes
B7: 01.00 | C7: TRABAJOS PRELIMINARES Y MOVIMIENTO DE TIERRAS | H7: Planificación e ingeniería base
B8: 01.01 | C8: Delimitación topográfica, replanteo de tizas e hitos | D8: glb | E8: 1 | F8: 15000 | G8: =E8*F8 | H8: Estacas de madera y teodolito
B9: 01.02 | C9: Movimiento de tierras, nivelación y compactado de vías | D9: m2 | E9: 17137.84 | F9: 6.5 | G9: =E9*F9 | H9: Uso de motoniveladora y rodillo en arena
B10: 02.00 | C10: INGRESO MONUMENTAL Y PÓRTICO DE ACCESO | H10: Acceso rústico e identidad visual
B11: 02.01 | C11: Pórtico monumental de troncos de eucalipto seco tratado | D11: glb | E11: 1 | F11: 45000 | G11: =E11*F11 | H11: Vigas y columnas de eucalipto seco de 8"-10"
B12: 02.02 | C12: Muros de pirca decorativa de piedra de cantera en pórtico | D12: m2 | E12: 120 | F12: 250 | G12: =E12*F12 | H12: Piedra caliza caliche dorada de Ica apilada
B13: 02.03 | C13: Caseta de vigilancia blindada y control de accesos | D13: und | E13: 1 | F13: 60000 | G13: =E13*F13 | H13: Estructura de concreto armado con cemento Tipo V
B14: 02.04 | C14: Portón rústico de madera shihuahuaco tratada para intemperie | D14: und | E14: 1 | F14: 15000 | G14: =E14*F14 | H14: Madera noble y herrajes de hierro forjado
B15: 03.00 | C15: CERCOS PERIMETRALES (PIRCAS DE SEGURIDAD) | H15: Protección perimetral integrada al paisaje
B16: 03.01 | C16: Cerco frontal de pirca de piedra natural (h=1.80m) | D16: m | E16: 450 | F16: 450 | G16: =E16*F16 | H16: Piedra caliza dorada de la región apilada a mano
B17: 03.02 | C17: Cerco de seguridad perimetral lateral y posterior ligero | D17: m | E17: 1200 | F17: 110 | G17: =E17*F17 | H17: Postes de eucalipto de 4" con alambre de púas
B18: 04.00 | C18: VÍAS INTERNAS Y CIRCULACIÓN (LIVING STREETS) | H18: Tránsito interno eco-eficiente
B19: 04.01 | C19: Afirmado y estabilización de vías con mezcla de arcilla y cal | D19: m2 | E19: 17137.84 | F19: 25 | G19: =E19*F19 | H19: Arcilla desértica compactada, libre de asfalto
B20: 04.02 | C20: Senderos peatonales ecológicos y alameda central | D20: m2 | E20: 3500 | F20: 18 | G20: =E20*F20 | H20: Arcilla fina compactada y bordes de piedra
B21: 05.00 | C21: CLUB OASIS Y ÁREAS RECREATIVAS COMUNES | H21: Corazón social y recreativo del condominio
B22: 05.01 | C22: Piscina Oasis central revestida con piedra de río | D22: m2 | E22: 395 | F22: 1200 | G22: =E22*F22 | H22: Revestimiento de piedra natural, filtros de cuarzo
B23: 05.02 | C23: Espejo de agua ornamental para relajación | D23: m2 | E23: 252 | F23: 650 | G23: =E23*F23 | H23: Lecho de piedra pulida y recirculación biológica
B24: 05.03 | C24: Decks de madera shihuahuaco tratada en zonas de descanso | D24: m2 | E24: 220 | F24: 380 | G24: =E24*F24 | H24: Madera machihembrada tratada contra intemperie
B25: 05.04 | C25: Fogón central (Fire Pit) integrado en piedra natural | D25: und | E25: 1 | F25: 25000 | G25: =E25*F25 | H25: Anillo de piedra con asientos integrados y gas
B26: 05.05 | C26: Xeripaisajismo y dunas ornamentales (cactus y agaves) | D26: glb | E26: 1 | F26: 50000 | G26: =E26*F26 | H26: Agave americano, cactus candelabro y bougainvilleas
B27: 06.00 | C27: INSTALACIONES SANITARIAS Y AGUA CONDOMINIAL | H27: Saneamiento ecológico e hídrico
B28: 06.01 | C28: Red de distribución de agua condominial a lotes | D28: m | E28: 2850 | F28: 85 | G28: =E28*F28 | H28: Tuberías de HDPE enterradas en zanja de arena
B29: 06.02 | C29: Cisterna central de almacenamiento de agua de 50m3 | D29: und | E29: 1 | F29: 120000 | G29: =E29*F29 | H29: Concreto armado Tipo V (protección de sulfatos)
B30: 06.03 | C30: Planta de Tratamiento de Aguas Residuales PTAR biológica | D30: und | E30: 1 | F30: 125000 | G30: =E30*F30 | H30: Sistema de lodos activos para reúso en riego
B31: 07.00 | C31: RED ELÉCTRICA ECO-SOLAR E ILUMINACIÓN COMÚN | H31: Iluminación limpia y carga limpia
B32: 07.01 | C32: Postes de iluminación vial autónomos con panel solar led | D32: und | E32: 95 | F32: 3500 | G32: =E32*F32 | H32: Postes de acero con luminaria led solar 60W
B33: 07.02 | C33: Pérgola fotovoltaica central y banco de baterías (Carga Buggy) | D33: glb | E33: 1 | F33: 120000 | G33: =E33*F33 | H33: Paneles solares monocristalinos y baterías de litio
C34: COSTO DIRECTO TOTAL DE OBRAS (CD) | G34: =SUM(G7:G33)
C35: Gastos Generales y Dirección Técnica (10%) | G35: =G34*0.1
C36: Utilidad del Contratista e Imprevistos (8%) | G36: =G34*0.08
C37: PRESUPUESTO TOTAL INVERSIÓN (CAPEX TOTAL) | G37: =G34+G35+G36
B39: Nota Técnica de Materiales: | C39: El presupuesto de obra civil se ha estimado con base en materiales rústicos de bajo mantenimiento y alta durabilidad para el desierto: - Piedra de Cantera local (pircas y muros de la caseta/pórtico), brindando estabilidad sísmica y aislamiento térmico natural. - Eucalipto seco tratado en troncos de 8"-10" y madera Shihuahuaco tratada para el pórtico, pérgolas, portón y decks. - Afirmado estabilizado en vías internas (cero asfalto) y postes led solares autónomos para un condominio de cero emisiones.

Sheet Flujo de Caja
B2: PROYECCIÓN DE FLUJO DE CAJA (HORIZONTE 24 MESES)
B3: Moon Paracas · Modelo de cobranza y pagos de obra por caja positiva
B5: 1. CRONOGRAMA DE VENTAS Y CRÉDITO DIRECTO (ENTRADAS Y SALIDAS DE CAJA)
B6: Mes | C6: Lotes Vend. | D6: P. Prom. Lote | E6: Ventas Lotes | F6: Coch. Vend. | G6: Ventas Coch. | H6: Ventas Totales | I6: Inicial Lotes (30%) | J6: Cobro Financ. (70%) | K6: Cocheras (100%) | L6: Total Ingresos | M6: CAPEX Obras | N6: Pago Terreno | O6: Comisiones (4%) | P6: Gtos. Admin/Leg | Q6: Total Egresos | R6: Flujo Neto | S6: Flujo Acumulado
B7: Mes 0 | C7: 0 | D7: 0 | E7: =C7*D7 | F7: 0 | G7: =F7*5000 | H7: =E7+G7 | I7: =E7*0.3 | J7: 0 | K7: =G7 | L7: =I7+J7+K7 | M7: 50000 | N7: 0 | O7: =H7*0.04 | P7: 0 | Q7: =M7+N7+O7+P7 | R7: =L7-Q7 | S7: =R7
B8: Mes 1 | C8: 13 | D8: 27445.15 | E8: =C8*D8 | F8: 6 | G8: =F8*5000 | H8: =E8+G8 | I8: =E8*0.3 | J8: 0 | K8: =G8 | L8: =I8+J8+K8 | M8: 150000 | N8: 37500 | O8: =H8*0.04 | P8: 15000 | Q8: =M8+N8+O8+P8 | R8: =L8-Q8 | S8: =S7+R8
B9: Mes 2 | C9: 13 | D9: 28567.62 | E9: =C9*D9 | F9: 6 | G9: =F9*5000 | H9: =E9+G9 | I9: =E9*0.3 | J9: =SUM(E8:E8)*0.7/12 | K9: =G9 | L9: =I9+J9+K9 | M9: 150000 | N9: 37500 | O9: =H9*0.04 | P9: 15000 | Q9: =M9+N9+O9+P9 | R9: =L9-Q9 | S9: =S8+R9
B10: Mes 3 | C10: 13 | D10: 18942 | E10: =C10*D10 | F10: 6 | G10: =F10*5000 | H10: =E10+G10 | I10: =E10*0.3 | J10: =SUM(E8:E9)*0.7/12 | K10: =G10 | L10: =I10+J10+K10 | M10: 150000 | N10: 37500 | O10: =H10*0.04 | P10: 15000 | Q10: =M10+N10+O10+P10 | R10: =L10-Q10 | S10: =S9+R10
B11: Mes 4 | C11: 16 | D11: 18544.75 | E11: =C11*D11 | F11: 6 | G11: =F11*5000 | H11: =E11+G11 | I11: =E11*0.3 | J11: =SUM(E8:E10)*0.7/12 | K11: =G11 | L11: =I11+J11+K11 | M11: 150000 | N11: 37500 | O11: =H11*0.04 | P11: 15000 | Q11: =M11+N11+O11+P11 | R11: =L11-Q11 | S11: =S10+R11
B12: Mes 5 | C12: 16 | D12: 12014.31 | E12: =C12*D12 | F12: 6 | G12: =F12*5000 | H12: =E12+G12 | I12: =E12*0.3 | J12: =SUM(E8:E11)*0.7/12 | K12: =G12 | L12: =I12+J12+K12 | M12: 150000 | N12: 37500 | O12: =H12*0.04 | P12: 15000 | Q12: =M12+N12+O12+P12 | R12: =L12-Q12 | S12: =S11+R12
B13: Mes 6 | C13: 16 | D13: 11832.38 | E13: =C13*D13 | F13: 6 | G13: =F13*5000 | H13: =E13+G13 | I13: =E13*0.3 | J13: =SUM(E8:E12)*0.7/12 | K13: =G13 | L13: =I13+J13+K13 | M13: 150000 | N13: 37500 | O13: =H13*0.04 | P13: 15000 | Q13: =M13+N13+O13+P13 | R13: =L13-Q13 | S13: =S12+R13
B14: Mes 7 | C14: 16 | D14: 11716.12 | E14: =C14*D14 | F14: 6 | G14: =F14*5000 | H14: =E14+G14 | I14: =E14*0.3 | J14: =SUM(E8:E13)*0.7/12 | K14: =G14 | L14: =I14+J14+K14 | M14: 130000 | N14: 37500 | O14: =H14*0.04 | P14: 15000 | Q14: =M14+N14+O14+P14 | R14: =L14-Q14 | S14: =S13+R14
B15: Mes 8 | C15: 16 | D15: 13842.62 | E15: =C15*D15 | F15: 6 | G15: =F15*5000 | H15: =E15+G15 | I15: =E15*0.3 | J15: =SUM(E8:E14)*0.7/12 | K15: =G15 | L15: =I15+J15+K15 | M15: 130000 | N15: 37500 | O15: =H15*0.04 | P15: 15000 | Q15: =M15+N15+O15+P15 | R15: =L15-Q15 | S15: =S14+R15
B16: Mes 9 | C16: 16 | D16: 22939.31 | E16: =C16*D16 | F16: 6 | G16: =F16*5000 | H16: =E16+G16 | I16: =E16*0.3 | J16: =SUM(E8:E15)*0.7/12 | K16: =G16 | L16: =I16+J16+K16 | M16: 130000 | N16: 37500 | O16: =H16*0.04 | P16: 15000 | Q16: =M16+N16+O16+P16 | R16: =L16-Q16 | S16: =S15+R16
B17: Mes 10 | C17: 16 | D17: 40012.5 | E17: =C17*D17 | F17: 6 | G17: =F17*5000 | H17: =E17+G17 | I17: =E17*0.3 | J17: =SUM(E8:E16)*0.7/12 | K17: =G17 | L17: =I17+J17+K17 | M17: 130000 | N17: 37500 | O17: =H17*0.04 | P17: 15000 | Q17: =M17+N17+O17+P17 | R17: =L17-Q17 | S17: =S16+R17
B18: Mes 11 | C18: 16 | D18: 39849.19 | E18: =C18*D18 | F18: 6 | G18: =F18*5000 | H18: =E18+G18 | I18: =E18*0.3 | J18: =SUM(E8:E17)*0.7/12 | K18: =G18 | L18: =I18+J18+K18 | M18: 130000 | N18: 37500 | O18: =H18*0.04 | P18: 15000 | Q18: =M18+N18+O18+P18 | R18: =L18-Q18 | S18: =S17+R18
B19: Mes 12 | C19: 16 | D19: 39078.06 | E19: =C19*D19 | F19: 6 | G19: =F19*5000 | H19: =E19+G19 | I19: =E19*0.3 | J19: =SUM(E8:E18)*0.7/12 | K19: =G19 | L19: =I19+J19+K19 | M19: 130000 | N19: 37500 | O19: =H19*0.04 | P19: 15000 | Q19: =M19+N19+O19+P19 | R19: =L19-Q19 | S19: =S18+R19
B20: Mes 13 | C20: 16 | D20: 13934.81 | E20: =C20*D20 | F20: 6 | G20: =F20*5000 | H20: =E20+G20 | I20: =E20*0.3 | J20: =SUM(E8:E19)*0.7/12 | K20: =G20 | L20: =I20+J20+K20 | M20: 150000 | N20: 37500 | O20: =H20*0.04 | P20: 15000 | Q20: =M20+N20+O20+P20 | R20: =L20-Q20 | S20: =S19+R20
B21: Mes 14 | C21: 16 | D21: 12975.31 | E21: =C21*D21 | F21: 6 | G21: =F21*5000 | H21: =E21+G21 | I21: =E21*0.3 | J21: =SUM(E9:E20)*0.7/12 | K21: =G21 | L21: =I21+J21+K21 | M21: 150000 | N21: 37500 | O21: =H21*0.04 | P21: 15000 | Q21: =M21+N21+O21+P21 | R21: =L21-Q21 | S21: =S20+R21
B22: Mes 15 | C22: 16 | D22: 12624.69 | E22: =C22*D22 | F22: 6 | G22: =F22*5000 | H22: =E22+G22 | I22: =E22*0.3 | J22: =SUM(E10:E21)*0.7/12 | K22: =G22 | L22: =I22+J22+K22 | M22: 150000 | N22: 37500 | O22: =H22*0.04 | P22: 15000 | Q22: =M22+N22+O22+P22 | R22: =L22-Q22 | S22: =S21+R22
B23: Mes 16 | C23: 16 | D23: 11093.56 | E23: =C23*D23 | F23: 6 | G23: =F23*5000 | H23: =E23+G23 | I23: =E23*0.3 | J23: =SUM(E11:E22)*0.7/12 | K23: =G23 | L23: =I23+J23+K23 | M23: 150000 | N23: 37500 | O23: =H23*0.04 | P23: 15000 | Q23: =M23+N23+O23+P23 | R23: =L23-Q23 | S23: =S22+R23
B24: Mes 17 | C24: 16 | D24: 14538.88 | E24: =C24*D24 | F24: 6 | G24: =F24*5000 | H24: =E24+G24 | I24: =E24*0.3 | J24: =SUM(E12:E23)*0.7/12 | K24: =G24 | L24: =I24+J24+K24 | M24: 150000 | N24: 37500 | O24: =H24*0.04 | P24: 15000 | Q24: =M24+N24+O24+P24 | R24: =L24-Q24 | S24: =S23+R24
B25: Mes 18 | C25: 16 | D25: 19410.25 | E25: =C25*D25 | F25: 6 | G25: =F25*5000 | H25: =E25+G25 | I25: =E25*0.3 | J25: =SUM(E13:E24)*0.7/12 | K25: =G25 | L25: =I25+J25+K25 | M25: 150000 | N25: 37500 | O25: =H25*0.04 | P25: 15000 | Q25: =M25+N25+O25+P25 | R25: =L25-Q25 | S25: =S24+R25
B26: Mes 19 | C26: 6 | D26: 20160 | E26: =C26*D26 | F26: 3 | G26: =F26*5000 | H26: =E26+G26 | I26: =E26*0.3 | J26: =SUM(E14:E25)*0.7/12 | K26: =G26 | L26: =I26+J26+K26 | M26: 95713.42 | N26: 37500 | O26: =H26*0.04 | P26: 15000 | Q26: =M26+N26+O26+P26 | R26: =L26-Q26 | S26: =S25+R26
B27: Mes 20 | C27: 6 | D27: 26374.17 | E27: =C27*D27 | F27: 3 | G27: =F27*5000 | H27: =E27+G27 | I27: =E27*0.3 | J27: =SUM(E15:E26)*0.7/12 | K27: =G27 | L27: =I27+J27+K27 | M27: 95713.42 | N27: 37500 | O27: =H27*0.04 | P27: 15000 | Q27: =M27+N27+O27+P27 | R27: =L27-Q27 | S27: =S26+R27
B28: Mes 21 | C28: 6 | D28: 27934.17 | E28: =C28*D28 | F28: 3 | G28: =F28*5000 | H28: =E28+G28 | I28: =E28*0.3 | J28: =SUM(E16:E27)*0.7/12 | K28: =G28 | L28: =I28+J28+K28 | M28: 95713.42 | N28: 37500 | O28: =H28*0.04 | P28: 15000 | Q28: =M28+N28+O28+P28 | R28: =L28-Q28 | S28: =S27+R28
B29: Mes 22 | C29: 6 | D29: 28171.5 | E29: =C29*D29 | F29: 3 | G29: =F29*5000 | H29: =E29+G29 | I29: =E29*0.3 | J29: =SUM(E17:E28)*0.7/12 | K29: =G29 | L29: =I29+J29+K29 | M29: 95713.42 | N29: 37500 | O29: =H29*0.04 | P29: 15000 | Q29: =M29+N29+O29+P29 | R29: =L29-Q29 | S29: =S28+R29
B30: Mes 23 | C30: 6 | D30: 29260.33 | E30: =C30*D30 | F30: 3 | G30: =F30*5000 | H30: =E30+G30 | I30: =E30*0.3 | J30: =SUM(E18:E29)*0.7/12 | K30: =G30 | L30: =I30+J30+K30 | M30: 95713.42 | N30: 37500 | O30: =H30*0.04 | P30: 15000 | Q30: =M30+N30+O30+P30 | R30: =L30-Q30 | S30: =S29+R30
B31: Mes 24 | C31: 3 | D31: 29409.67 | E31: =C31*D31 | F31: 2 | G31: =F31*5000 | H31: =E31+G31 | I31: =E31*0.3 | J31: =SUM(E19:E30)*0.7/12 | K31: =G31 | L31: =I31+J31+K31 | M31: 95713.42 | N31: 37500 | O31: =H31*0.04 | P31: 15000 | Q31: =M31+N31+O31+P31 | R31: =L31-Q31 | S31: =S30+R31
B32: TOTALES | C32: =SUM(C7:C31) | D32: =AVERAGE(D7:D31) | E32: =SUM(E7:E31) | F32: =SUM(F7:F31) | G32: =SUM(G7:G31) | H32: =SUM(H7:H31) | I32: =SUM(I7:I31) | J32: =SUM(J7:J31) | K32: =SUM(K7:K31) | L32: =SUM(L7:L31) | ... R32: =SUM(R7:R31) | S32: =S31
